smart_git_ai-0.1.6.dist-info/licenses/LICENSE
smartgit/__init__.py
smartgit/py.typed
smartgit/cache/__init__.py
smartgit/cache/base.py
smartgit/cache/manager.py
smartgit/cache/memory_cache.py
smartgit/cache/sqlite_cache.py
smartgit/cli/__init__.py
smartgit/cli/main.py
smartgit/core/__init__.py
smartgit/core/exceptions.py
smartgit/core/models.py
smartgit/core/repository.py
smartgit/providers/__init__.py
smartgit/providers/anthropic_provider.py
smartgit/providers/base.py
smartgit/providers/factory.py
smartgit/providers/openai_provider.py
smartgit/services/__init__.py
smartgit/services/cache_warmer.py
smartgit/services/commit_analyzer.py
smartgit/services/commit_generator.py
smartgit/services/config.py
smartgit/services/hooks.py
smartgit/utils/__init__.py
smartgit/utils/git_helpers.py
smart_git_ai-0.1.6.dist-info/METADATA
smart_git_ai-0.1.6.dist-info/WHEEL
smart_git_ai-0.1.6.dist-info/entry_points.txt
smart_git_ai-0.1.6.dist-info/top_level.txt
smart_git_ai-0.1.6.dist-info/RECORD
