Metadata-Version: 2.4
Name: smart-git-ai
Version: 0.1.6
Summary: AI-powered git commit message generator and git utility toolkit
Author-email: Master Shifu <sifatibna.amin9@gmail.com>
License: MIT
Project-URL: Homepage, https://github.com/SifatIbna/smart-git-ai
Project-URL: Repository, https://github.com/SifatIbna/smart-git-ai
Project-URL: Issues, https://github.com/SifatIbna/smart-git-ai/issues
Classifier: Development Status :: 3 - Alpha
Classifier: Intended Audience :: Developers
Classifier: License :: OSI Approved :: MIT License
Classifier: Programming Language :: Python :: 3
Classifier: Programming Language :: Python :: 3.8
Classifier: Programming Language :: Python :: 3.9
Classifier: Programming Language :: Python :: 3.10
Classifier: Programming Language :: Python :: 3.11
Classifier: Programming Language :: Python :: 3.12
Requires-Python: >=3.8
License-File: LICENSE
Requires-Dist: click>=8.0.0
Requires-Dist: gitpython>=3.1.0
Requires-Dist: anthropic>=0.18.0
Requires-Dist: openai>=1.12.0
Requires-Dist: rich>=13.0.0
Requires-Dist: python-dotenv>=1.0.0
Requires-Dist: pyyaml>=6.0.0
Requires-Dist: pydantic>=2.6.0
Requires-Dist: pydantic-settings>=2.1.0
Requires-Dist: prompt-toolkit>=3.0.43
Provides-Extra: dev
Requires-Dist: pytest>=7.0.0; extra == "dev"
Requires-Dist: pytest-cov>=4.0.0; extra == "dev"
Requires-Dist: black>=23.0.0; extra == "dev"
Requires-Dist: ruff>=0.2.0; extra == "dev"
Requires-Dist: isort>=5.12.0; extra == "dev"
Requires-Dist: mypy>=1.0.0; extra == "dev"
Requires-Dist: pre-commit>=3.0.0; extra == "dev"
Requires-Dist: types-pyyaml>=6.0.0; extra == "dev"
Dynamic: license-file
